AUTHORS
LICENCE
MANIFEST.in
README.rst
requirements.txt
setup.py
webassets_react/__init__.py
webassets_react/filter.py
webassets_react.egg-info/PKG-INFO
webassets_react.egg-info/SOURCES.txt
webassets_react.egg-info/dependency_links.txt
webassets_react.egg-info/not-zip-safe
webassets_react.egg-info/requires.txt
webassets_react.egg-info/top_level.txt