Metadata-Version: 1.1
Name: webassets-react
Version: 1.0.1
Summary: The webassets filter for transform React JSX to JS.
Home-page: http://github.com/dotnetage/webassets-react
Author: Ray
Author-email: csharp2002@hotmail.com
License: BSD
Keywords: webassets,react,jsx
Platform: any
Classifier: Development Status :: 5 - Production/Stable
Classifier: Intended Audience :: Developers
Classifier: License :: OSI Approved :: BSD License
Classifier: Natural Language :: English
Classifier: Operating System :: OS Independent
Classifier: Programming Language :: Python :: 2.7
Classifier: Topic :: Software Development :: Libraries
Classifier: Topic :: Utilities
